example/__init__.py
example/__main__.py
example/demo.py
ns_prodsec_defectdojo_cli-1.0.0.dist-info/licenses/LICENSE
ns_prodsec_defectdojo_cli-1.0.0.dist-info/METADATA
ns_prodsec_defectdojo_cli-1.0.0.dist-info/WHEEL
ns_prodsec_defectdojo_cli-1.0.0.dist-info/entry_points.txt
ns_prodsec_defectdojo_cli-1.0.0.dist-info/top_level.txt
ns_prodsec_defectdojo_cli-1.0.0.dist-info/RECORD
