Metadata-Version: 2.4
Name: ns-prodsec-defectdojo-cli
Version: 1.0.0
Summary: package example
Author-email: Filipe Pina <shelf-corncob-said@duck.com>
Project-URL: Homepage, https://github.com/fopinappb/test-something
Requires-Python: >=3.10
License-File: LICENSE
Dynamic: license-file
